README.rst
icssplit.py
setup.py
icssplit.egg-info/PKG-INFO
icssplit.egg-info/SOURCES.txt
icssplit.egg-info/dependency_links.txt
icssplit.egg-info/entry_points.txt
icssplit.egg-info/requires.txt
icssplit.egg-info/top_level.txt