Metadata-Version: 1.2
Name: icssplit
Version: 1.0.1
Summary: Split big .ics/.ical files into smaller ones for easy import into Google Calendar
Home-page: https://github.com/beorn/icssplit
Author: Bjorn Stabell
Author-email: bjorn@stabell.org
License: MIT
Download-URL: https://github.com/beorn/icssplit/archive/1.0.0.tar.gz
Keywords: ics calendar ical vcal google gcal
Platform: UNKNOWN
Classifier: Development Status :: 5 - Production/Stable
Classifier: Programming Language :: Python
Classifier: Programming Language :: Python :: 3
Classifier: Programming Language :: Python :: 3 :: Only
Classifier: Programming Language :: Python :: 3.6
Classifier: Programming Language :: Python :: 3.7
Classifier: License :: OSI Approved :: MIT License
Classifier: Environment :: Console
Classifier: Intended Audience :: End Users/Desktop
Classifier: Intended Audience :: System Administrators
Classifier: Topic :: Office/Business :: Scheduling
Requires-Python: ~=3.0
